{
  "indexes": [
    {
      "collectionGroup": "transactions",
      "queryScope": "COLLECTION",
      "fields": [
        {"fieldPath": "userId", "order": "ASCENDING"},
        {"fieldPath": "isDeleted", "order": "ASCENDING"},
        {"fieldPath": "date", "order": "DESCENDING"}
      ]
    },
    {
      "collectionGroup": "transactions",
      "queryScope": "COLLECTION",
      "fields": [
        {"fieldPath": "userId", "order": "ASCENDING"},
        {"fieldPath": "type", "order": "ASCENDING"},
        {"fieldPath": "isDeleted", "order": "ASCENDING"},
        {"fieldPath": "date", "order": "DESCENDING"}
      ]
    },
    {
      "collectionGroup": "transactions",
      "queryScope": "COLLECTION",
      "fields": [
        {"fieldPath": "userId", "order": "ASCENDING"},
        {"fieldPath": "isDeleted", "order": "ASCENDING"},
        {"fieldPath": "date", "order": "ASCENDING"},
        {"fieldPath": "date", "order": "DESCENDING"}
      ]
    },
    {
      "collectionGroup": "transactions",
      "queryScope": "COLLECTION",
      "fields": [
        {"fieldPath": "userId", "order": "ASCENDING"},
        {"fieldPath": "smsId", "order": "ASCENDING"}
      ]
    },
    {
      "collectionGroup": "loans",
      "queryScope": "COLLECTION",
      "fields": [
        {"fieldPath": "userId", "order": "ASCENDING"},
        {"fieldPath": "isDeleted", "order": "ASCENDING"},
        {"fieldPath": "dueDate", "order": "ASCENDING"}
      ]
    },
    {
      "collectionGroup": "loans",
      "queryScope": "COLLECTION",
      "fields": [
        {"fieldPath": "userId", "order": "ASCENDING"},
        {"fieldPath": "type", "order": "ASCENDING"},
        {"fieldPath": "isDeleted", "order": "ASCENDING"},
        {"fieldPath": "dueDate", "order": "ASCENDING"}
      ]
    },
    {
      "collectionGroup": "reminders",
      "queryScope": "COLLECTION",
      "fields": [
        {"fieldPath": "userId", "order": "ASCENDING"},
        {"fieldPath": "isDeleted", "order": "ASCENDING"},
        {"fieldPath": "dueDate", "order": "ASCENDING"}
      ]
    }
  ],
  "fieldOverrides": []
}
